LICENSE.txt
MANIFEST.in
README.rst
example.py
setup.cfg
setup.py
PyLC.egg-info/PKG-INFO
PyLC.egg-info/SOURCES.txt
PyLC.egg-info/dependency_links.txt
PyLC.egg-info/top_level.txt
pylc/__init__.py
pylc/lc.py
pylc/resources.py
pylc/utils.py