Metadata-Version: 1.1
Name: PyLC
Version: 0.1.0a15
Summary: A python wrapper for the Lending Club API
Home-page: https://github.com/bmorrise/pylc
Author: Benjamin Morrise
Author-email: bmorrise@gmail.com
License: MIT
Platform: UNKNOWN
Classifier: Development Status :: 3 - Alpha
Classifier: Programming Language :: Python :: 2
Classifier: Programming Language :: Python :: 2.6
Classifier: Programming Language :: Python :: 2.7
